[
  {
    "id": "classic-gold",
    "label": "Classic Gold & Marble",
    "description": "White marble base with luminous gold foiling and gentle sparkles.",
    "palette": {
      "background": "#f8f6f2",
      "accent": "#d4af37",
      "accentSoft": "#f4e3c3",
      "text": "#2f2721",
      "textMuted": "rgba(47, 39, 33, 0.72)",
      "glass": "rgba(255, 255, 255, 0.72)",
      "border": "rgba(210, 177, 107, 0.42)"
    },
    "fonts": {
      "heading": "'Playfair Display', serif",
      "body": "'Inter', sans-serif"
    },
    "toggles": {
      "sparkles": true,
      "glow": true,
      "animationIntensity": "medium",
      "sparkleAmount": 0.55,
      "lightBokeh": false,
      "petals": false,
      "vignetteStrength": 0.35,
      "paperTexture": true,
      "goldFoilIntensity": 0.62,
      "waxSealShape": "round",
      "cardEdgeStyle": "rounded"
    },
    "assets": {
      "waxSealVariant": "gold"
    }
  },
  {
    "id": "champagne-garden",
    "label": "Champagne Garden",
    "description": "Champagne ivory glass with garden evening glow and refined sparkles.",
    "palette": {
      "background": "#fbf6ee",
      "accent": "#c9b28b",
      "accentSoft": "#f4e8d4",
      "text": "#2a241d",
      "textMuted": "rgba(42, 36, 29, 0.68)",
      "glass": "rgba(255, 252, 246, 0.78)",
      "border": "rgba(201, 178, 139, 0.36)"
    },
    "fonts": {
      "heading": "'Didot', 'Playfair Display', serif",
      "body": "'Source Sans 3', sans-serif"
    },
    "toggles": {
      "sparkles": true,
      "glow": true,
      "animationIntensity": "medium",
      "sparkleAmount": 0.6,
      "lightBokeh": true,
      "petals": false,
      "vignetteStrength": 0.42,
      "paperTexture": true,
      "goldFoilIntensity": 0.68,
      "waxSealShape": "oval",
      "cardEdgeStyle": "soft-bevel"
    },
    "assets": {
      "waxSealVariant": "gold"
    }
  },
  {
    "id": "pearl-sage",
    "label": "Pearl & Sage",
    "description": "Pearled whites with sage greenery and calm emerald accents.",
    "palette": {
      "background": "#f7f9f4",
      "accent": "#4b8063",
      "accentSoft": "#cfe3d6",
      "text": "#253028",
      "textMuted": "rgba(37, 48, 40, 0.7)",
      "glass": "rgba(250, 255, 250, 0.74)",
      "border": "rgba(75, 128, 99, 0.28)"
    },
    "fonts": {
      "heading": "'Cinzel', serif",
      "body": "'Inter', sans-serif"
    },
    "toggles": {
      "sparkles": true,
      "glow": true,
      "animationIntensity": "gentle",
      "sparkleAmount": 0.48,
      "lightBokeh": false,
      "petals": false,
      "vignetteStrength": 0.28,
      "paperTexture": true,
      "goldFoilIntensity": 0.5,
      "waxSealShape": "round",
      "cardEdgeStyle": "rounded"
    },
    "assets": {
      "waxSealVariant": "emerald"
    }
  },
  {
    "id": "ivory-dusty-pink",
    "label": "Ivory & Dusty Pink",
    "description": "Ivory silk with romantic dusty rose, perfect for blush engagements.",
    "palette": {
      "background": "#fdf7f8",
      "accent": "#c77a8a",
      "accentSoft": "#f5c6d2",
      "text": "#2b1e24",
      "textMuted": "rgba(43, 30, 36, 0.7)",
      "glass": "rgba(255, 244, 248, 0.82)",
      "border": "rgba(199, 122, 138, 0.32)"
    },
    "fonts": {
      "heading": "'Parisienne', cursive",
      "body": "'Lato', sans-serif"
    },
    "toggles": {
      "sparkles": true,
      "glow": true,
      "animationIntensity": "gentle",
      "sparkleAmount": 0.68,
      "lightBokeh": true,
      "petals": true,
      "vignetteStrength": 0.4,
      "paperTexture": true,
      "goldFoilIntensity": 0.64,
      "waxSealShape": "floral",
      "cardEdgeStyle": "deckled"
    },
    "assets": {
      "waxSealVariant": "rosegold"
    }
  },
  {
    "id": "royal-emerald-gold",
    "label": "Royal Emerald & Gold",
    "description": "Deep emerald stone with opulent gold foiling and evening glow.",
    "palette": {
      "background": "#f6f4ee",
      "accent": "#0f766e",
      "accentSoft": "#9fe8d8",
      "text": "#1e1b16",
      "textMuted": "rgba(30, 27, 22, 0.68)",
      "glass": "rgba(247, 250, 249, 0.74)",
      "border": "rgba(33, 133, 120, 0.35)"
    },
    "fonts": {
      "heading": "'Cinzel', serif",
      "body": "'Source Sans 3', sans-serif"
    },
    "toggles": {
      "sparkles": true,
      "glow": true,
      "animationIntensity": "grand",
      "sparkleAmount": 0.54,
      "lightBokeh": true,
      "petals": false,
      "vignetteStrength": 0.48,
      "paperTexture": true,
      "goldFoilIntensity": 0.72,
      "waxSealShape": "oval",
      "cardEdgeStyle": "soft-bevel"
    },
    "assets": {
      "waxSealVariant": "emerald"
    }
  },
  {
    "id": "ivory-gold-classic",
    "label": "Ivory Gold (Classic)",
    "description": "Timeless ivory marble with champagne gold foil and soft sparkles.",
    "palette": {
      "background": "#fbf9f3",
      "accent": "#d3b36b",
      "accentSoft": "#f4e6cd",
      "text": "#2f261f",
      "textMuted": "rgba(47, 38, 31, 0.72)",
      "glass": "rgba(255, 252, 244, 0.78)",
      "border": "rgba(211, 179, 107, 0.34)"
    },
    "fonts": {
      "heading": "'Playfair Display', serif",
      "body": "'Inter', sans-serif"
    },
    "toggles": {
      "sparkles": true,
      "glow": true,
      "animationIntensity": "gentle",
      "sparkleAmount": 0.52,
      "lightBokeh": false,
      "petals": false,
      "vignetteStrength": 0.32,
      "paperTexture": true,
      "goldFoilIntensity": 0.62,
      "foilSheenIntensity": 0.62,
      "waxSealShape": "round",
      "cardEdgeStyle": "rounded",
      "showArabicText": true
    },
    "assets": {
      "waxSealVariant": "gold"
    }
  },
  {
    "id": "blush-silk-gold",
    "label": "Blush Silk + Gold",
    "description": "Blush silk gradients with warm gold foil and romantic glow.",
    "palette": {
      "background": "#fdf7f9",
      "accent": "#d89aa8",
      "accentSoft": "#f6d8df",
      "text": "#2e1c24",
      "textMuted": "rgba(46, 28, 36, 0.7)",
      "glass": "rgba(255, 244, 248, 0.85)",
      "border": "rgba(216, 154, 168, 0.3)"
    },
    "fonts": {
      "heading": "'Parisienne', cursive",
      "body": "'Lato', sans-serif"
    },
    "toggles": {
      "sparkles": true,
      "glow": true,
      "animationIntensity": "gentle",
      "sparkleAmount": 0.7,
      "lightBokeh": true,
      "petals": true,
      "vignetteStrength": 0.4,
      "paperTexture": true,
      "goldFoilIntensity": 0.66,
      "foilSheenIntensity": 0.66,
      "waxSealShape": "oval",
      "cardEdgeStyle": "deckled",
      "showArabicText": true
    },
    "assets": {
      "waxSealVariant": "rosegold"
    }
  },
  {
    "id": "emerald-malachite-gold",
    "label": "Emerald Malachite + Gold",
    "description": "Striking malachite textures with glowing gold foil and evening bokeh.",
    "palette": {
      "background": "#f3f6f2",
      "accent": "#0f8a70",
      "accentSoft": "#b1e5d4",
      "text": "#1d201d",
      "textMuted": "rgba(29, 32, 29, 0.68)",
      "glass": "rgba(246, 252, 248, 0.78)",
      "border": "rgba(15, 138, 112, 0.32)"
    },
    "fonts": {
      "heading": "'Cinzel', serif",
      "body": "'Source Sans 3', sans-serif"
    },
    "toggles": {
      "sparkles": true,
      "glow": true,
      "animationIntensity": "grand",
      "sparkleAmount": 0.56,
      "lightBokeh": true,
      "petals": false,
      "vignetteStrength": 0.46,
      "paperTexture": true,
      "goldFoilIntensity": 0.72,
      "foilSheenIntensity": 0.72,
      "waxSealShape": "round",
      "cardEdgeStyle": "soft-bevel",
      "showArabicText": true
    },
    "assets": {
      "waxSealVariant": "emerald"
    }
  },
  {
    "id": "pearl-lavender-rose-gold",
    "label": "Pearl Lavender + Rose Gold",
    "description": "Lavender pearl hues with rose gold foil and airy shimmer.",
    "palette": {
      "background": "#f6f3fb",
      "accent": "#c79bbd",
      "accentSoft": "#eadbf0",
      "text": "#2d2230",
      "textMuted": "rgba(45, 34, 48, 0.68)",
      "glass": "rgba(251, 247, 255, 0.78)",
      "border": "rgba(199, 155, 189, 0.32)"
    },
    "fonts": {
      "heading": "'Didot', 'Playfair Display', serif",
      "body": "'Inter', sans-serif"
    },
    "toggles": {
      "sparkles": true,
      "glow": true,
      "animationIntensity": "gentle",
      "sparkleAmount": 0.58,
      "lightBokeh": true,
      "petals": false,
      "vignetteStrength": 0.38,
      "paperTexture": true,
      "goldFoilIntensity": 0.64,
      "foilSheenIntensity": 0.64,
      "waxSealShape": "floral",
      "cardEdgeStyle": "rounded",
      "showArabicText": true
    },
    "assets": {
      "waxSealVariant": "flower"
    }
  },
  {
    "id": "black-onyx-champagne",
    "label": "Black Onyx + Champagne Gold",
    "description": "Evening gala black onyx with glowing champagne foils.",
    "palette": {
      "background": "#f4f1ed",
      "accent": "#d5b98b",
      "accentSoft": "#f0dfc3",
      "text": "#1b1916",
      "textMuted": "rgba(27, 25, 22, 0.72)",
      "glass": "rgba(255, 252, 246, 0.82)",
      "border": "rgba(213, 185, 139, 0.4)"
    },
    "fonts": {
      "heading": "'Cormorant Garamond', serif",
      "body": "'Source Sans 3', sans-serif"
    },
    "toggles": {
      "sparkles": true,
      "glow": true,
      "animationIntensity": "grand",
      "sparkleAmount": 0.48,
      "lightBokeh": false,
      "petals": false,
      "vignetteStrength": 0.52,
      "paperTexture": true,
      "goldFoilIntensity": 0.74,
      "foilSheenIntensity": 0.74,
      "waxSealShape": "oval",
      "cardEdgeStyle": "bevel",
      "showArabicText": true
    },
    "assets": {
      "waxSealVariant": "gold"
    }
  },
  {
    "id": "desert-sand-warm-gold",
    "label": "Desert Sand + Warm Gold",
    "description": "Desert sands with warm golden hour glow and gentle vignette.",
    "palette": {
      "background": "#f9f3ea",
      "accent": "#c99a5e",
      "accentSoft": "#f3ddba",
      "text": "#2f241a",
      "textMuted": "rgba(47, 36, 26, 0.7)",
      "glass": "rgba(255, 249, 239, 0.8)",
      "border": "rgba(201, 154, 94, 0.35)"
    },
    "fonts": {
      "heading": "'Cinzel', serif",
      "body": "'Inter', sans-serif"
    },
    "toggles": {
      "sparkles": true,
      "glow": true,
      "animationIntensity": "medium",
      "sparkleAmount": 0.5,
      "lightBokeh": false,
      "petals": false,
      "vignetteStrength": 0.44,
      "paperTexture": true,
      "goldFoilIntensity": 0.68,
      "foilSheenIntensity": 0.68,
      "waxSealShape": "round",
      "cardEdgeStyle": "soft-bevel",
      "showArabicText": true
    },
    "assets": {
      "waxSealVariant": "gold"
    }
  },
  {
    "id": "midnight-garden",
    "label": "Midnight Garden",
    "description": "Midnight noir with rose gold foiling for a black-tie garden reception.",
    "palette": {
      "background": "#1a1714",
      "accent": "#d4af8c",
      "accentSoft": "#8f6b4d",
      "text": "#f8f5ef",
      "textMuted": "rgba(248, 245, 239, 0.7)",
      "glass": "rgba(28, 24, 22, 0.72)",
      "border": "rgba(212, 175, 140, 0.38)"
    },
    "fonts": {
      "heading": "'Great Vibes', cursive",
      "body": "'Josefin Sans', sans-serif"
    },
    "toggles": {
      "sparkles": true,
      "glow": true,
      "animationIntensity": "grand",
      "sparkleAmount": 0.7,
      "lightBokeh": true,
      "petals": true,
      "vignetteStrength": 0.58,
      "paperTexture": true,
      "goldFoilIntensity": 0.8,
      "waxSealShape": "floral",
      "cardEdgeStyle": "bevel"
    },
    "assets": {
      "waxSealVariant": "rosegold"
    }
  },
  {
    "id": "blush-marble",
    "label": "Blush Marble",
    "description": "Soft blush marble with satin highlights and delicate shimmer.",
    "palette": {
      "background": "#f9f1f2",
      "accent": "#d9a5b2",
      "accentSoft": "#f7dce2",
      "text": "#3a2a30",
      "textMuted": "rgba(58, 42, 48, 0.68)",
      "glass": "rgba(255, 246, 248, 0.8)",
      "border": "rgba(217, 165, 178, 0.32)"
    },
    "fonts": {
      "heading": "'Alex Brush', cursive",
      "body": "'Lato', sans-serif"
    },
    "toggles": {
      "sparkles": true,
      "glow": true,
      "animationIntensity": "gentle",
      "sparkleAmount": 0.64,
      "lightBokeh": true,
      "petals": true,
      "vignetteStrength": 0.38,
      "paperTexture": true,
      "goldFoilIntensity": 0.66,
      "waxSealShape": "round",
      "cardEdgeStyle": "deckled"
    },
    "assets": {
      "waxSealVariant": "rosegold"
    }
  },
  {
    "id": "pearl-minimal",
    "label": "Pearl Islamic Minimal",
    "description": "Pure white pearl with subtle gold and refined serif typography.",
    "palette": {
      "background": "#fdfcf8",
      "accent": "#d0b176",
      "accentSoft": "#f2e3c7",
      "text": "#2a2520",
      "textMuted": "rgba(42, 37, 32, 0.6)",
      "glass": "rgba(255, 255, 255, 0.76)",
      "border": "rgba(208, 177, 118, 0.32)"
    },
    "fonts": {
      "heading": "'Scheherazade New', serif",
      "body": "'Inter', sans-serif"
    },
    "toggles": {
      "sparkles": false,
      "glow": true,
      "animationIntensity": "gentle",
      "sparkleAmount": 0.25,
      "lightBokeh": false,
      "petals": false,
      "vignetteStrength": 0.3,
      "paperTexture": true,
      "goldFoilIntensity": 0.48,
      "waxSealShape": "oval",
      "cardEdgeStyle": "rounded"
    },
    "assets": {
      "waxSealVariant": "gold"
    }
  },
  {
    "id": "modern-arabic",
    "label": "Modern Arabic Script",
    "description": "Neutral stone with Arabic typography accents and modern sans body.",
    "palette": {
      "background": "#f5f2ed",
      "accent": "#b69a73",
      "accentSoft": "#e7d8c2",
      "text": "#302923",
      "textMuted": "rgba(48, 41, 35, 0.7)",
      "glass": "rgba(249, 246, 240, 0.78)",
      "border": "rgba(182, 154, 115, 0.32)"
    },
    "fonts": {
      "heading": "'Amiri', serif",
      "body": "'Nunito', sans-serif"
    },
    "toggles": {
      "sparkles": true,
      "glow": true,
      "animationIntensity": "medium",
      "sparkleAmount": 0.44,
      "lightBokeh": false,
      "petals": false,
      "vignetteStrength": 0.34,
      "paperTexture": true,
      "goldFoilIntensity": 0.58,
      "waxSealShape": "round",
      "cardEdgeStyle": "soft-bevel"
    },
    "assets": {
      "waxSealVariant": "gold"
    }
  },
  {
    "id": "ivory-gold-classic",
    "label": "Ivory Gold",
    "description": "Classic ivory marble with champagne gold foiling and soft vignette.",
    "palette": {
      "background": "#f9f6f2",
      "accent": "#d4b276",
      "accentSoft": "#efe2cc",
      "text": "#2d2420",
      "textMuted": "rgba(45, 36, 32, 0.68)",
      "glass": "rgba(255, 255, 255, 0.74)",
      "border": "rgba(206, 174, 122, 0.38)"
    },
    "fonts": {
      "heading": "'Playfair Display', serif",
      "body": "'Inter', sans-serif"
    },
    "toggles": {
      "sparkles": true,
      "glow": true,
      "animationIntensity": "medium",
      "sparkleAmount": 0.52,
      "lightBokeh": false,
      "petals": false,
      "vignetteStrength": 0.3,
      "paperTexture": true,
      "goldFoilIntensity": 0.66,
      "waxSealShape": "round",
      "cardEdgeStyle": "rounded"
    },
    "assets": {
      "waxSealVariant": "gold"
    }
  },
  {
    "id": "blush-silk-gold",
    "label": "Blush Silk + Gold",
    "description": "Blush silk gradients with molten gold foil and romantic sparkles.",
    "palette": {
      "background": "#f8f1ee",
      "accent": "#d6a98c",
      "accentSoft": "#f4d6c6",
      "text": "#2f2721",
      "textMuted": "rgba(47, 39, 33, 0.7)",
      "glass": "rgba(255, 247, 243, 0.78)",
      "border": "rgba(214, 169, 140, 0.4)"
    },
    "fonts": {
      "heading": "'Didot', 'Playfair Display', serif",
      "body": "'Lato', sans-serif"
    },
    "toggles": {
      "sparkles": true,
      "glow": true,
      "animationIntensity": "gentle",
      "sparkleAmount": 0.6,
      "lightBokeh": true,
      "petals": true,
      "vignetteStrength": 0.28,
      "paperTexture": true,
      "goldFoilIntensity": 0.58,
      "waxSealShape": "oval",
      "cardEdgeStyle": "soft-bevel"
    },
    "assets": {
      "waxSealVariant": "rosegold"
    }
  },
  {
    "id": "emerald-malachite",
    "label": "Emerald Malachite + Gold",
    "description": "Deep emerald malachite veining with radiant gold foil and evening glow.",
    "palette": {
      "background": "#123b36",
      "accent": "#c8b17a",
      "accentSoft": "#2b594f",
      "text": "#f5f0e8",
      "textMuted": "rgba(245, 240, 232, 0.78)",
      "glass": "rgba(12, 47, 42, 0.72)",
      "border": "rgba(200, 177, 122, 0.48)"
    },
    "fonts": {
      "heading": "'Cinzel', serif",
      "body": "'Source Sans 3', sans-serif"
    },
    "toggles": {
      "sparkles": false,
      "glow": true,
      "animationIntensity": "grand",
      "sparkleAmount": 0.35,
      "lightBokeh": true,
      "petals": false,
      "vignetteStrength": 0.46,
      "paperTexture": false,
      "goldFoilIntensity": 0.72,
      "waxSealShape": "round",
      "cardEdgeStyle": "bevel"
    },
    "assets": {
      "waxSealVariant": "emerald"
    }
  },
  {
    "id": "pearl-lavender-rose",
    "label": "Pearl Lavender + Rose Gold",
    "description": "Pearlescent lavender with rose-gold shimmer and airy sparkle.",
    "palette": {
      "background": "#f5f2f8",
      "accent": "#d9a6b4",
      "accentSoft": "#f3ddec",
      "text": "#2f2531",
      "textMuted": "rgba(47, 37, 49, 0.68)",
      "glass": "rgba(255, 255, 255, 0.78)",
      "border": "rgba(217, 166, 180, 0.4)"
    },
    "fonts": {
      "heading": "'Cormorant Garamond', serif",
      "body": "'Nunito', sans-serif"
    },
    "toggles": {
      "sparkles": true,
      "glow": true,
      "animationIntensity": "medium",
      "sparkleAmount": 0.68,
      "lightBokeh": true,
      "petals": true,
      "vignetteStrength": 0.34,
      "paperTexture": true,
      "goldFoilIntensity": 0.55,
      "waxSealShape": "floral",
      "cardEdgeStyle": "deckled"
    },
    "assets": {
      "waxSealVariant": "flower"
    }
  },
  {
    "id": "desert-sand-gold",
    "label": "Desert Sand + Warm Gold",
    "description": "Desert sunset neutrals with warm gold foil and soft vignette glow.",
    "palette": {
      "background": "#f3ede4",
      "accent": "#c89b5d",
      "accentSoft": "#ead6b9",
      "text": "#2d2218",
      "textMuted": "rgba(45, 34, 24, 0.7)",
      "glass": "rgba(255, 249, 240, 0.78)",
      "border": "rgba(200, 155, 93, 0.42)"
    },
    "fonts": {
      "heading": "'Cinzel', serif",
      "body": "'Inter', sans-serif"
    },
    "toggles": {
      "sparkles": true,
      "glow": true,
      "animationIntensity": "medium",
      "sparkleAmount": 0.48,
      "lightBokeh": false,
      "petals": false,
      "vignetteStrength": 0.36,
      "paperTexture": true,
      "goldFoilIntensity": 0.6,
      "waxSealShape": "oval",
      "cardEdgeStyle": "soft-bevel"
    },
    "assets": {
      "waxSealVariant": "gold"
    }
  }
]
